LOTR/__init__.py
LOTR/lotr.py
avisochek_sdk-0.0.2.dist-info/LICENSE
avisochek_sdk-0.0.2.dist-info/METADATA
avisochek_sdk-0.0.2.dist-info/WHEEL
avisochek_sdk-0.0.2.dist-info/top_level.txt
avisochek_sdk-0.0.2.dist-info/RECORD
