Metadata-Version: 2.1
Name: avisochek-sdk
Version: 0.0.2
Summary: Get information on characters, quotes and more from the lord of the rings.
Home-page: https://github.com/avisochek/avisochek-sdk
Author: Allan Visochek
Author-email: allan@example.com
License: UNKNOWN
Project-URL: Bug Tracker, https://github.com/avisochek/avisochek-sdk/issues
Platform: UNKNOWN
Classifier: Programming Language :: Python :: 3
Classifier: License :: OSI Approved :: MIT License
Classifier: Operating System :: OS Independent
Requires-Python: >=3.6
License-File: LICENSE
